pf_dre_core/__init__.py
pf_dre_core/mms/__init__.py
pf_dre_core/mms/base.py
pf_dre_core/mms/client.py
pf_dre_core/mms/forecast_ts_client.py
pf_dre_core/mms/helpers.py
pf_dre_core/mms/real_time_ts_client.py
pf_dre_core/mms/simulation_ts_client.py
pf_dre_core/mms/ts_client.py
pf_dre_core/time_metrics/__init__.py
pf_dre_core/time_metrics/client.py
pf_dre_core/utils/__init__.py
pf_dre_core/utils/config.py
pf_dre_core/utils/datetimes.py
pf_dre_core/utils/loader.py
pf_dre_core-1.0.11.dist-info/LICENSE
pf_dre_core-1.0.11.dist-info/METADATA
pf_dre_core-1.0.11.dist-info/WHEEL
pf_dre_core-1.0.11.dist-info/top_level.txt
pf_dre_core-1.0.11.dist-info/RECORD
