Metadata-Version: 2.1
Name: pf-dre-core
Version: 1.0.11
Summary: Core library used by DRE and MMS Tools & Subsystems
Home-page: UNKNOWN
Author: Dominic Hains
Author-email: d.hains@uq.edu.au
License: UNKNOWN
Platform: UNKNOWN
Classifier: Programming Language :: Python :: 3.8
Classifier: Programming Language :: Python :: 3.7
Classifier: License :: OSI Approved :: GNU General Public License v3 or later (GPLv3+)
Classifier: Intended Audience :: Developers
Classifier: Operating System :: OS Independent
Requires-Python: >=3.7
License-File: LICENSE
Requires-Dist: psycopg2-binary
Requires-Dist: pandas
Requires-Dist: pyYAML
Requires-Dist: python-dotenv
Requires-Dist: astral
Requires-Dist: boto3 (==1.15.18)
